stellar_base/__init__.py
stellar_base/address.py
stellar_base/asset.py
stellar_base/base58.py
stellar_base/builder.py
stellar_base/exceptions.py
stellar_base/federation.py
stellar_base/horizon.py
stellar_base/keypair.py
stellar_base/memo.py
stellar_base/network.py
stellar_base/operation.py
stellar_base/purecrc16.py
stellar_base/transaction.py
stellar_base/transaction_envelope.py
stellar_base/utils.py
stellar_base/version.py
stellar_base/stellarxdr/StellarXDR_const.py
stellar_base/stellarxdr/StellarXDR_pack.py
stellar_base/stellarxdr/StellarXDR_type.py
stellar_base/stellarxdr/__init__.py
stellar_base/stellarxdr/updatexdr.py
stellar_base/stellarxdr/xdrgen.py
stellar_base/wordlist/chinese.txt
stellar_base-1.1.2.0.dist-info/DESCRIPTION.rst
stellar_base-1.1.2.0.dist-info/METADATA
stellar_base-1.1.2.0.dist-info/RECORD
stellar_base-1.1.2.0.dist-info/WHEEL
stellar_base-1.1.2.0.dist-info/metadata.json
stellar_base-1.1.2.0.dist-info/top_level.txt
tests/__init__.py
tests/conftest.py
tests/test_address.py
tests/test_asset.py
tests/test_builder.py
tests/test_envelope.py
tests/test_federation.py
tests/test_horizon.py
tests/test_keypair.py
tests/test_memo.py
tests/test_network.py
tests/test_operation.py
tests/test_transaction.py
tests/test_utils.py
