Metadata-Version: 1.2
Name: stellar-base
Version: 1.1.2.0
Summary: Conservative Version of library for managing Stellar.org blockchain transactions and accounts 
Home-page: http://github.com/stellarCN/py-stellar-base/
Author: Eno, overcat
Author-email: appweb.cn@gmail.com, 4catcode@gmail.com
Maintainer: antb123
Maintainer-email: awbarker@gmail.com
License: Apache
Keywords: stellar.org,lumens,xlm,blockchain,distributed exchange,cryptocurrency,dex,stellar-core,horizon,sdex,trading,Stellar
Platform: UNKNOWN
Classifier: Development Status :: 5 - Production/Stable
Classifier: Intended Audience :: Developers
Classifier: Intended Audience :: Financial and Insurance Industry
Classifier: License :: OSI Approved :: Apache Software License
Classifier: Operating System :: OS Independent
Classifier: Programming Language :: Python
Classifier: Programming Language :: Python :: 2.7
Classifier: Programming Language :: Python :: 3
Classifier: Programming Language :: Python :: 3.6
Classifier: Programming Language :: Python :: 3.7
Classifier: Topic :: Software Development :: Libraries :: Python Modules
